cleaning_agent/__init__.py
cleaning_agent/agent.py
cleaning_agent/cli.py
cleaning_agent/config.py
cleaning_agent/constants.py
cleaning_agent/models.py
cleaning_agent/utils.py
cleaning_agent-0.1.8.dist-info/METADATA
cleaning_agent-0.1.8.dist-info/WHEEL
cleaning_agent-0.1.8.dist-info/entry_points.txt
cleaning_agent-0.1.8.dist-info/top_level.txt
cleaning_agent-0.1.8.dist-info/RECORD
