Metadata-Version: 2.4
Name: cleaning-agent
Version: 0.1.8
Summary: Intelligent data cleaning agent for automated data quality improvement
Author-email: StepFunction AI <team@stepfunction.ai>
Maintainer-email: StepFunction AI <team@stepfunction.ai>
License-Expression: MIT
Project-URL: Homepage, https://github.com/stepfnAI/cleaning-agent
Project-URL: Documentation, https://cleaning-agent.readthedocs.io
Project-URL: Repository, https://github.com/stepfnAI/cleaning-agent.git
Project-URL: Issues, https://github.com/stepfnAI/cleaning-agent/issues
Project-URL: Changelog, https://github.com/stepfnAI/cleaning-agent/blob/main/CHANGELOG.md
Keywords: data-cleaning,data-quality,ai-agent,machine-learning,data-preprocessing
Classifier: Development Status :: 3 - Alpha
Classifier: Intended Audience :: Developers
Classifier: Programming Language :: Python :: 3
Classifier: Programming Language :: Python :: 3.9
Classifier: Programming Language :: Python :: 3.10
Classifier: Programming Language :: Python :: 3.11
Classifier: Programming Language :: Python :: 3.12
Requires-Python: >=3.10
Requires-Dist: python-dotenv
Requires-Dist: sfn-blueprint>=0.7.4
Provides-Extra: dev
Requires-Dist: pytest>=7.0.0; extra == "dev"
Requires-Dist: pytest-cov>=4.0.0; extra == "dev"
Requires-Dist: black>=23.0.0; extra == "dev"
Requires-Dist: isort>=5.12.0; extra == "dev"
Requires-Dist: flake8>=6.0.0; extra == "dev"
Requires-Dist: mypy>=1.0.0; extra == "dev"
Provides-Extra: test
Requires-Dist: pytest>=7.0.0; extra == "test"
Requires-Dist: pytest-cov>=4.0.0; extra == "test"
Requires-Dist: pytest-mock>=3.10.0; extra == "test"
Provides-Extra: docs
Requires-Dist: sphinx>=6.0.0; extra == "docs"
Requires-Dist: sphinx-rtd-theme>=1.2.0; extra == "docs"
Requires-Dist: myst-parser>=1.0.0; extra == "docs"
